pygments_lexer_ursa/lexer.py
pygments_lexer_ursa-1.0.12.dist-info/.bak.0.PKG-INFO
pygments_lexer_ursa-1.0.12.dist-info/.bak.0.SOURCES.txt
pygments_lexer_ursa-1.0.12.dist-info/LICENSE
pygments_lexer_ursa-1.0.12.dist-info/METADATA
pygments_lexer_ursa-1.0.12.dist-info/WHEEL
pygments_lexer_ursa-1.0.12.dist-info/entry_points.txt
pygments_lexer_ursa-1.0.12.dist-info/top_level.txt
pygments_lexer_ursa-1.0.12.dist-info/RECORD
