Metadata-Version: 2.1
Name: pygments-lexer-ursa
Version: 1.0.12
Summary: Pygments lexer for Ursa
Author-email: Reuben Thomas <rrt@sc3d.org>
License: MIT
Project-URL: Homepage, https://github.com/ursalang/pygments-lexer-ursa
Classifier: Environment :: Console
Classifier: Programming Language :: Python :: 3
Requires-Python: >=3.8
License-File: LICENSE
Requires-Dist: pygments
